{"header":"PROCESSED on Sat, 19 Jun 2021 03:14:26 +0000 from http:\/\/localhost:8085\/","files":{"jquery-core":{"url":"\/wp-includes\/js\/jquery\/jquery.min.js","success":true},"jquery-migrate":{"url":"\/wp-includes\/js\/jquery\/jquery-migrate.min.js","success":true},"wp-polyfill":{"url":"\/wp-includes\/js\/dist\/vendor\/wp-polyfill.min.js","success":true},"wp-dom-ready":{"url":"\/wp-includes\/js\/dist\/dom-ready.min.js","success":true},"wpautoterms_base":{"url":"\/wp-content\/plugins\/auto-terms-of-service-and-privacy-policy\/js\/base.js","success":true}}}